eegpp3/TOKEN.txt
eegpp3/__init__.py
eegpp3/__main__.py
eegpp3/dataloader.py
eegpp3/dataset.py
eegpp3/inference.py
eegpp3/logger.py
eegpp3/overwrite_template.py
eegpp3/params.py
eegpp3/trainer.py
eegpp3/trainer_backup.py
eegpp3/visualization.py
eegpp3/configs/__init__.py
eegpp3/configs/cnn1d_config.yml
eegpp3/configs/fft2cwout_config.yml
eegpp3/configs/fftcnn1dnc_config.yml
eegpp3/configs/ffttransnc_config.yml
eegpp3/configs/stftcnn1dnc_config.yml
eegpp3/configs/stfttransnc_config.yml
eegpp3/configs/transformer_config.yml
eegpp3/configs/wtcnn1dnc_config.yml
eegpp3/configs/wtresnet501dnc_config.yml
eegpp3/data/__init__.py
eegpp3/models/__init__.py
eegpp3/models/cnn1d2c.py
eegpp3/models/fft2c.py
eegpp3/models/fftcnn1dnc.py
eegpp3/models/ffttransnc.py
eegpp3/models/stft2c.py
eegpp3/models/stftcnn1dnc.py
eegpp3/models/stfttransnc.py
eegpp3/models/wtcnn1dnc.py
eegpp3/models/wtresnet1dnc.py
eegpp3/models/baseline/__init__.py
eegpp3/models/baseline/cnn1d.py
eegpp3/models/baseline/fft.py
eegpp3/models/baseline/resnet.py
eegpp3/models/baseline/transformer.py
eegpp3/out/__init__.py
eegpp3/utils/__init__.py
eegpp3/utils/common_utils.py
eegpp3/utils/config_utils.py
eegpp3/utils/data_utils.py
eegpp3/utils/model_utils.py
eegpp3_beta-2.0.dist-info/licenses/LICENSE
eegpp3_beta-2.0.dist-info/METADATA
eegpp3_beta-2.0.dist-info/WHEEL
eegpp3_beta-2.0.dist-info/top_level.txt
eegpp3_beta-2.0.dist-info/RECORD
