Metadata-Version: 2.4
Name: eegpp3-beta
Version: 2.0
Summary: EEG Phrase Predictor ver 3
Author-email: "Duc Anh Nguyen, Vu An Tuan" <vuanhtuan1407@gmail.com>
Classifier: Programming Language :: Python :: 3
Classifier: License :: OSI Approved :: MIT License
Classifier: Operating System :: OS Independent
Requires-Python: >=3.10
License-File: LICENSE
Requires-Dist: dropbox>=12.0.2
Requires-Dist: joblib>=1.4.2
Requires-Dist: numpy>=2.1.1
Requires-Dist: tqdm>=4.66.5
Requires-Dist: torchinfo>=1.8.0
Requires-Dist: scipy>=1.14.1
Requires-Dist: pyyaml>=6.0.2
Requires-Dist: pywavelets>=1.7.0
Requires-Dist: ptwt>=0.1.9
Requires-Dist: pandas>=2.2.2
Requires-Dist: lightning>=2.4.0
Requires-Dist: scikit-learn>=1.5.2
Requires-Dist: seaborn>=0.13.2
Dynamic: license-file
